test.py
pipemaker/__init__.py
pipemaker/examples/__init__.py
pipemaker/examples/example1.py
pipemaker/examples/example1_luigi.py
pipemaker/filesystem/__init__.py
pipemaker/filesystem/creds.py
pipemaker/filesystem/filepath.py
pipemaker/filesystem/filedrivers/__init__.py
pipemaker/filesystem/filedrivers/csv.py
pipemaker/filesystem/filedrivers/pandas.py
pipemaker/filesystem/filedrivers/pkl.py
pipemaker/filesystem/filedrivers/xlsx.py
pipemaker/master/__init__.py
pipemaker/master/controller.py
pipemaker/master/pipeline.py
pipemaker/master/scheduler.py
pipemaker/master/step.py
pipemaker/qpython/__init__.py
pipemaker/qpython/eventq.py
pipemaker/qpython/loghandler.py
pipemaker/qpython/taskq.py
pipemaker/qpython/workerq.py
pipemaker/qrabbit/__init__.py
pipemaker/qrabbit/eventq.py
pipemaker/qrabbit/loghandler.py
pipemaker/qrabbit/pika.py
pipemaker/qrabbit/taskq.py
pipemaker/qrabbit/workerq.py
pipemaker/test/.coveragerc
pipemaker/test/__init__.py
pipemaker/test/conftest.py
pipemaker/test/pytest.ini
pipemaker/test/test_filepath.py
pipemaker/test/test_pipeline.py
pipemaker/test/test_rabbitmq.py
pipemaker/test/test_utils.py
pipemaker/utils/__init__.py
pipemaker/utils/babies-first-names-top-100-girls.csv
pipemaker/utils/cellevents.py
pipemaker/utils/defaultlog.py
pipemaker/utils/dotdict.py
pipemaker/utils/ipstartup.py
pipemaker/utils/retry.py
pipemaker/utils/share.py
pipemaker/web/__init__.py
pipemaker/web/view.py
pipemaker/web/static/style.css
pipemaker/web/templates/view.html
pipemaker/worker/__init__.py
pipemaker/worker/task.py
pipemaker-1.0.9.data/data/etc/.pipemaker/config.yaml
pipemaker-1.0.9.data/data/etc/.pipemaker/creds.yaml
pipemaker-1.0.9.dist-info/LICENSE.txt
pipemaker-1.0.9.dist-info/METADATA
pipemaker-1.0.9.dist-info/WHEEL
pipemaker-1.0.9.dist-info/top_level.txt
pipemaker-1.0.9.dist-info/RECORD
